gisty.py
get_gisty-0.1.2.dist-info/METADATA
get_gisty-0.1.2.dist-info/RECORD
get_gisty-0.1.2.dist-info/WHEEL
get_gisty-0.1.2.dist-info/top_level.txt
