Metadata-Version: 2.1
Name: get-gisty
Version: 0.1.2
Summary: A an easy to use gist api.
Home-page: https://github.com/erinxocon/get-gisty
Author: Erin O'Connell
Author-email: erinocon5@gmail.com
License: MIT
Platform: UNKNOWN
Classifier: License :: OSI Approved :: MIT License
Classifier: Programming Language :: Python
Classifier: Programming Language :: Python :: 3.6
Classifier: Programming Language :: Python :: Implementation :: CPython
Classifier: Intended Audience :: Developers
Requires-Python: >=3.6.0
Requires-Dist: requests
